shiboken2/__init__.py
shiboken2/_config.py
shiboken2/_git_shiboken_module_version.py
shiboken2/concrt140.dll
shiboken2/msvcp140.dll
shiboken2/msvcp140_1.dll
shiboken2/msvcp140_2.dll
shiboken2/msvcp140_codecvt_ids.dll
shiboken2/shiboken2.abi3.dll
shiboken2/shiboken2.abi3.lib
shiboken2/shiboken2.pyd
shiboken2/ucrtbase.dll
shiboken2/vcamp140.dll
shiboken2/vccorlib140.dll
shiboken2/vcomp140.dll
shiboken2/vcruntime140.dll
shiboken2/docs/shiboken2/.buildinfo
shiboken2/docs/shiboken2/Shiboken.qch
shiboken2/docs/shiboken2/Shiboken.qhcp
shiboken2/docs/shiboken2/Shiboken.qhp
shiboken2/docs/shiboken2/Shiboken.qhp.bak
shiboken2/docs/shiboken2/considerations.html
shiboken2/docs/shiboken2/gettingstarted.html
shiboken2/docs/shiboken2/index.html
shiboken2/docs/shiboken2/py-modindex.html
shiboken2/docs/shiboken2/shibokengenerator.html
shiboken2/docs/shiboken2/shibokenmodule.html
shiboken2/docs/shiboken2/typesystem.html
shiboken2/docs/shiboken2/typesystem_arguments.html
shiboken2/docs/shiboken2/typesystem_codegeneration.html
shiboken2/docs/shiboken2/typesystem_codeinjection.html
shiboken2/docs/shiboken2/typesystem_conversionrule.html
shiboken2/docs/shiboken2/typesystem_converters.html
shiboken2/docs/shiboken2/typesystem_documentation.html
shiboken2/docs/shiboken2/typesystem_manipulating_objects.html
shiboken2/docs/shiboken2/typesystem_modify_function.html
shiboken2/docs/shiboken2/typesystem_ownership.html
shiboken2/docs/shiboken2/typesystem_sequenceprotocol.html
shiboken2/docs/shiboken2/typesystem_solving_compilation.html
shiboken2/docs/shiboken2/typesystem_specifying_types.html
shiboken2/docs/shiboken2/typesystem_templates.html
shiboken2/docs/shiboken2/typesystem_variables.html
shiboken2/docs/shiboken2/.doctrees/considerations.doctree
shiboken2/docs/shiboken2/.doctrees/environment.pickle
shiboken2/docs/shiboken2/.doctrees/gettingstarted.doctree
shiboken2/docs/shiboken2/.doctrees/index.doctree
shiboken2/docs/shiboken2/.doctrees/shibokengenerator.doctree
shiboken2-5.15.2.1.dist-info/LICENSE.COMMERCIAL
shiboken2-5.15.2.1.dist-info/LICENSE.FDL
shiboken2-5.15.2.1.dist-info/LICENSE.GPL2
shiboken2-5.15.2.1.dist-info/LICENSE.GPLv3
shiboken2-5.15.2.1.dist-info/LICENSE.GPLv3-EXCEPT
shiboken2-5.15.2.1.dist-info/LICENSE.LGPLv3
shiboken2-5.15.2.1.dist-info/METADATA
shiboken2-5.15.2.1.dist-info/WHEEL
shiboken2-5.15.2.1.dist-info/top_level.txt
shiboken2-5.15.2.1.dist-info/RECORD
